isosegdenoise/Assets/LICENSE_files/LICENSE-BSD-primary.txt
isosegdenoise/Assets/LICENSE_files/LICENSE-MIT.txt
isosegdenoise/Assets/LICENSE_files/LICENSE-other-non-commercial.txt
isosegdenoise/Assets/ctkThemeBuilderThemes/Anthracite.json
isosegdenoise/Assets/ctkThemeBuilderThemes/Cobalt.json
isosegdenoise/Assets/ctkThemeBuilderThemes/GhostTrain.json
isosegdenoise/Assets/ctkThemeBuilderThemes/Greengage.json
isosegdenoise/Assets/ctkThemeBuilderThemes/Hades.json
isosegdenoise/Assets/ctkThemeBuilderThemes/Harlequin.json
isosegdenoise/Assets/ctkThemeBuilderThemes/License_of_these_themes(MIT)/LICENSE.txt
isosegdenoise/Assets/ctkThemeBuilderThemes/MoonlitSky.json
isosegdenoise/Assets/ctkThemeBuilderThemes/NeonBanana.json
isosegdenoise/Assets/ctkThemeBuilderThemes/NightTrain.json
isosegdenoise/Assets/ctkThemeBuilderThemes/Oceanix.json
isosegdenoise/Assets/ctkThemeBuilderThemes/Sweetkind.json
isosegdenoise/Assets/ctkThemeBuilderThemes/TestCard.json
isosegdenoise/Assets/dir_choice.txt
isosegdenoise/Assets/theme.txt
isosegdenoise/Executable.py
isosegdenoise/__init__.py
isosegdenoise/app_entry.py
isosegdenoise/processing_GUI.py
isosegdenoise/processing_class.py
isosegdenoise/sharedClasses.py
isosegdenoise/vendors/_apeerometiff.py
isosegdenoise/vendors/_deepcell.py
isosegdenoise/vendors/_steinbock.py
isosegdenoise/vendors/mesmer.onnx
isosegdenoise-0.2.4.dist-info/LICENSE-BSD-primary.txt
isosegdenoise-0.2.4.dist-info/LICENSE-MIT.txt
isosegdenoise-0.2.4.dist-info/LICENSE-other-non-commercial.txt
isosegdenoise-0.2.4.dist-info/METADATA
isosegdenoise-0.2.4.dist-info/WHEEL
isosegdenoise-0.2.4.dist-info/entry_points.txt
isosegdenoise-0.2.4.dist-info/RECORD
