Metadata-Version: 2.3
Name: isosegdenoise
Version: 0.2.4
Summary: A GUI for Deepcell and Cellpose segmentation / denoising, for integrating into PalmettoBUG without triggering GPL3 restrictions. Can be launched on its own to do denoising and cell segmentation separate from PalmettoBUG -- but requires / assumes a PalmettoBUG like directory structure.
License: Multiple: BSD-3, MIT, academic / non-commercial
Author: Ben Caiello
Author-email: <caiello@musc.edu>
Requires-Python: >=3.10
Classifier: License :: Other/Proprietary License
Classifier: Programming Language :: Python :: 3
Classifier: Programming Language :: Python :: 3.10
Provides-Extra: tensorflow
Requires-Dist: PySide6 (<6.5)
Requires-Dist: cellpose (>=3.0.8)
Requires-Dist: customtkinter (>=5.2.2)
Requires-Dist: defusedxml
Requires-Dist: keras (<3.0.0) ; extra == "tensorflow"
Requires-Dist: napari
Requires-Dist: numpy (<2.0.0)
Requires-Dist: onnx2torch
Requires-Dist: opencv-python-headless
Requires-Dist: pandas (>=2.0)
Requires-Dist: scikit-image (>=0.22.0)
Requires-Dist: scikit-learn
Requires-Dist: scipy
Requires-Dist: tensorflow (>=2.8.0,<=2.13) ; extra == "tensorflow"
Requires-Dist: tensorflow-addons (>=0.16.1) ; extra == "tensorflow"
Requires-Dist: tifffile (>=2024.2.12)
Requires-Dist: torch
